osducli/VERSION
osducli/__init__.py
osducli/__main__.py
osducli/click_cli.py
osducli/cliclient.py
osducli/config.py
osducli/log.py
osducli/state.py
osducli/version.py
osducli/wbddms_client.py
osducli/auth/__init__.py
osducli/auth/aws_token_credential.py
osducli/auth/credentials.py
osducli/auth/msal_interactive.py
osducli/auth/msal_non_interactive.py
osducli/auth/token_credential.py
osducli/commands/__init__.py
osducli/commands/config/__init__.py
osducli/commands/config/consts.py
osducli/commands/config/default.py
osducli/commands/config/info.py
osducli/commands/config/list.py
osducli/commands/config/update.py
osducli/commands/crs/__init__.py
osducli/commands/crs/_const.py
osducli/commands/crs/areas.py
osducli/commands/crs/info.py
osducli/commands/crs/list.py
osducli/commands/crs/summary.py
osducli/commands/crs/transforms.py
osducli/commands/dataload/__init__.py
osducli/commands/dataload/checkrefs.py
osducli/commands/dataload/ingest.py
osducli/commands/dataload/status.py
osducli/commands/dataload/verify.py
osducli/commands/entitlements/__init__.py
osducli/commands/entitlements/_const.py
osducli/commands/entitlements/info.py
osducli/commands/entitlements/mygroups.py
osducli/commands/entitlements/groups/__init__.py
osducli/commands/entitlements/groups/add.py
osducli/commands/entitlements/groups/delete.py
osducli/commands/entitlements/groups/members.py
osducli/commands/entitlements/members/__init__.py
osducli/commands/entitlements/members/add.py
osducli/commands/entitlements/members/groups.py
osducli/commands/entitlements/members/list.py
osducli/commands/entitlements/members/remove.py
osducli/commands/file/__init__.py
osducli/commands/file/_const.py
osducli/commands/file/download.py
osducli/commands/file/info.py
osducli/commands/file/metadata.py
osducli/commands/legal/__init__.py
osducli/commands/legal/_const.py
osducli/commands/legal/add.py
osducli/commands/legal/delete.py
osducli/commands/legal/info.py
osducli/commands/legal/listtags.py
osducli-0.0.52.dist-info/licenses/LICENSE.md
osducli-0.0.52.dist-info/METADATA
osducli-0.0.52.dist-info/WHEEL
osducli-0.0.52.dist-info/entry_points.txt
osducli-0.0.52.dist-info/top_level.txt
osducli-0.0.52.dist-info/RECORD
