Metadata-Version: 2.4
Name: osducli
Version: 0.0.52
Summary: OSDU command line
Author: OSDU Community
License-Expression: Apache-2.0
Project-URL: homepage, https://community.opengroup.org/osdu/platform/data-flow/data-loading/osdu-cli
Project-URL: issue-tracker, https://community.opengroup.org/osdu/platform/data-flow/data-loading/osdu-cli/-/issues
Keywords: osdu
Classifier: Development Status :: 3 - Alpha
Classifier: Environment :: Console
Classifier: Natural Language :: English
Classifier: Programming Language :: Python :: 3.13
Requires-Python: >=3.13
License-File: LICENSE.md
Requires-Dist: click
Requires-Dist: jmespath
Requires-Dist: osdu-api[common]==1.0.3
Requires-Dist: requests
Requires-Dist: tabulate
Requires-Dist: packaging
Requires-Dist: wbdutil==0.1.1
Requires-Dist: msal
Requires-Dist: msal-extensions
Requires-Dist: azure-identity
Requires-Dist: azure-keyvault
Requires-Dist: boto3
Requires-Dist: google
Requires-Dist: google-auth
Requires-Dist: google-auth-oauthlib
Requires-Dist: google-cloud-storage
Provides-Extra: dev
Requires-Dist: black; extra == "dev"
Requires-Dist: isort; extra == "dev"
Requires-Dist: pylint; extra == "dev"
Requires-Dist: ruff; extra == "dev"
Requires-Dist: pytest; extra == "dev"
Requires-Dist: pytest-mock; extra == "dev"
Requires-Dist: pytest-cov; extra == "dev"
Requires-Dist: mock; extra == "dev"
Requires-Dist: testfixtures; extra == "dev"
Requires-Dist: setuptools; extra == "dev"
Requires-Dist: tox; extra == "dev"
Requires-Dist: docutils; extra == "dev"
Dynamic: license-file
